{
  "users": [
    {
      "mail": "ademorotis@gmail.com",
      "password": "renaissance",
      "email": "ademorotis@gmail.com",
      "num": "+2349026906034"
    },
    {
      "mail": "ademorotis@gmail.com",
      "password": "renaissance",
      "email": "ademorotis@gmail.com",
      "num": "+2348151154410"
    },
    {
      "mail": "oluwashaeyhoon@gmail.com",
      "password": "renaissance",
      "email": "oluwashaeyhoon@gmail.com",
      "num": "+2348033188845"
    },
    {
      "email": "oluwashaeyhoon@gmail.com",
      "mail": "oluwashaeyhoon@gmail.com",
      "password": "renaissance",
      "num": "+2349026906034"
    }
  ]
}
